qvd-0.0.15.dist-info/METADATA
qvd-0.0.15.dist-info/WHEEL
qvd/test_files/AAPL.csv
qvd/test_files/test_qvd.qvd
qvd/test_files/test_qvd_null.qvd
qvd/test_files/AAPL.qvd
qvd/test_qvd_reader.py
qvd/qvd_reader.py
qvd/__init__.py
qvd/qvd.cpython-310-x86_64-linux-gnu.so
qvd-0.0.15.dist-info/RECORD
