Metadata-Version: 2.1
Name: qvd
Version: 0.0.15
Summary: A library for reading Qlik Sense .qvd file format from Python, written in Rust.
Keywords: python,rust,qlik,sense,qvd
Author: Sam Bentley <samtbentley@gmail.com>
Author-email: Sam Bentley <samtbentley@gmail.com>
License: Apache-2.0
Project-URL: Source Code, https://github.com/SBentley/qvd-utils
